llama_index/llms/octoai/__init__.py
llama_index/llms/octoai/base.py
llama_index/llms/octoai/utils.py
llama_index_llms_octoai-0.5.1.dist-info/METADATA
llama_index_llms_octoai-0.5.1.dist-info/WHEEL
llama_index_llms_octoai-0.5.1.dist-info/licenses/LICENSE
llama_index_llms_octoai-0.5.1.dist-info/RECORD
