Metadata-Version: 2.4
Name: llama-index-llms-octoai
Version: 0.5.1
Summary: llama-index llms octoai integration
Author: hanscl
License-Expression: MIT
License-File: LICENSE
Requires-Python: <4.0,>=3.9
Requires-Dist: boto3<2,>=1.35.3
Requires-Dist: llama-index-core<0.15,>=0.13.0
Requires-Dist: octoai<2,>=1.6.0
